_meraki.abi3.so
cpp_meraki-0.5.2.dist-info/RECORD
cpp_meraki-0.5.2.dist-info/LICENSE
cpp_meraki-0.5.2.dist-info/WHEEL
cpp_meraki-0.5.2.dist-info/top_level.txt
cpp_meraki-0.5.2.dist-info/METADATA
meraki/__init__.py
meraki/_build.py
