Metadata-Version: 2.1
Name: cpp-meraki
Version: 0.5.2
Summary: C/C++ implementation of Meraki - the Telestai Proof of Work algorithm
Home-page: https://github.com/Telestai-Project/meraki
Author: Ahmed Bodiwala
Author-email: Ahmed Bodiwala <admin@multicoin.co>
License: Apache-2.0
Classifier: License :: OSI Approved :: Apache Software License
Classifier: Programming Language :: C
Classifier: Programming Language :: C++
Classifier: Programming Language :: Python :: 3
Classifier: Programming Language :: Python :: 3.5
Classifier: Programming Language :: Python :: 3.6
Classifier: Programming Language :: Python :: 3.7
Requires-Python: >=3.8
License-File: LICENSE
